aptiviti_odbc/__init__.py
aptiviti_odbc-1.2.0.dist-info/LICENSE
aptiviti_odbc-1.2.0.dist-info/METADATA
aptiviti_odbc-1.2.0.dist-info/WHEEL
aptiviti_odbc-1.2.0.dist-info/top_level.txt
aptiviti_odbc-1.2.0.dist-info/RECORD
