Metadata-Version: 2.1
Name: aptiviti-odbc
Version: 1.2.0
Summary: Useful helper functions for constructing database queries
Home-page: https://github.com/aptiviti/aptiviti-odbc
Author: Daniel Fredriksen
Author-email: df@etr.ai
License: AGPLv3
Platform: UNKNOWN
